django_happy_decorators/manage.py
django_happy_decorators/decorators/__init__.py
django_happy_decorators/decorators/asgi.py
django_happy_decorators/decorators/fetch_object_or_404.py
django_happy_decorators/decorators/fetch_object_or_None.py
django_happy_decorators/decorators/if_not.py
django_happy_decorators/decorators/rate_limit.py
django_happy_decorators/decorators/settings.py
django_happy_decorators/decorators/tests.py
django_happy_decorators/decorators/urls.py
django_happy_decorators/decorators/wsgi.py
django_rate_limit/manage.py
django_rate_limit/django_rate_limit/__init__.py
django_rate_limit/django_rate_limit/asgi.py
django_rate_limit/django_rate_limit/rate_limit.py
django_rate_limit/django_rate_limit/settings.py
django_rate_limit/django_rate_limit/urls.py
django_rate_limit/django_rate_limit/wsgi.py
django_happy_decorators-0.2.11.dist-info/LICENSE
django_happy_decorators-0.2.11.dist-info/METADATA
django_happy_decorators-0.2.11.dist-info/WHEEL
django_happy_decorators-0.2.11.dist-info/top_level.txt
django_happy_decorators-0.2.11.dist-info/RECORD
